{
    "paths": {},
    "uuids": [
        "0a8z+LRRJFL4/64Bdc7nZ8",
        "11uCRMttlFd7N+YnuVInhI",
        "1fJ/4G+aJKgbzDCwH/yncM",
        "3e2Ug6031GmYdik5kQw+En",
        "42ZifUFO9HG6/unBZYJRqs",
        "49LBk7l6RC87epam5M7MDp",
        "49rdgPL/RCTbhX6q/M//KB",
        "550RC5urZNnZQWA+RpBPo1",
        "80x7HnHfdPx5TlxTBzhCDt",
        "8fi6VPcPZMoYbZ3dvYXnad",
        "97fP6bIcdJjrBgVBgAURqL",
        "a70y/BSilJHqXiCJIGPTXQ",
        "c6tf0Tan9Bh4cWEYnl0Twn",
        "dcGU8ayKVGyqr58Dtwl0r1",
        "ecpdLyjvZBwrvm+cedCcQy",
        "f3d5R3fb9HUZAvmFlzcgFS"
    ],
    "scenes": {
        "db://assets/game.fire": "1fJ/4G+aJKgbzDCwH/yncM"
    },
    "redirect": [
        "ecpdLyjvZBwrvm+cedCcQy",
        0
    ],
    "deps": [
        "internal"
    ],
    "packs": {
        "0c036a627": [
            "11uCRMttlFd7N+YnuVInhI",
            "1fJ/4G+aJKgbzDCwH/yncM",
            "42ZifUFO9HG6/unBZYJRqs",
            "49LBk7l6RC87epam5M7MDp",
            "49rdgPL/RCTbhX6q/M//KB",
            "550RC5urZNnZQWA+RpBPo1",
            "8fi6VPcPZMoYbZ3dvYXnad",
            "97fP6bIcdJjrBgVBgAURqL",
            "a70y/BSilJHqXiCJIGPTXQ",
            "dcGU8ayKVGyqr58Dtwl0r1"
        ],
        "0cabef185": [
            "0a8z+LRRJFL4/64Bdc7nZ8",
            "3e2Ug6031GmYdik5kQw+En",
            "80x7HnHfdPx5TlxTBzhCDt",
            "c6tf0Tan9Bh4cWEYnl0Twn",
            "f3d5R3fb9HUZAvmFlzcgFS"
        ]
    },
    "name": "main",
    "importBase": "import",
    "nativeBase": "native",
    "debug": true,
    "isZip": false,
    "encrypted": false,
    "versions": {
        "import": [
            "0c036a627",
            "4d50b",
            "0cabef185",
            "1a784"
        ],
        "native": [
            "0a8z+LRRJFL4/64Bdc7nZ8",
            "0c687",
            "3e2Ug6031GmYdik5kQw+En",
            "5fdc8",
            "550RC5urZNnZQWA+RpBPo1",
            "fe7c9",
            "80x7HnHfdPx5TlxTBzhCDt",
            "c0cb3",
            "c6tf0Tan9Bh4cWEYnl0Twn",
            "4b0bd",
            "dcGU8ayKVGyqr58Dtwl0r1",
            "74fd1",
            "f3d5R3fb9HUZAvmFlzcgFS",
            "c1880"
        ]
    }
}